cencus_consumer_complaint_executor/__init__.py
cencus_consumer_complaint_executor/zip_csv_executor.py
census_consumer_complaint_component/__init__.py
census_consumer_complaint_component/component.py
census_consumer_complaint_component/data_ingestion.py
census_consumer_complaint_component/data_preprocessing.py
census_consumer_complaint_component/data_validation.py
census_consumer_complaint_component/model_evaluation.py
census_consumer_complaint_component/model_pusher.py
census_consumer_complaint_component/model_trainer.py
census_consumer_complaint_component/feature_engineering/__init__.py
census_consumer_complaint_component/feature_engineering/feature_engineering.py
census_consumer_complaint_component/model_training/__init__.py
census_consumer_complaint_component/model_training/trainer.py
census_consumer_complaint_config/__init__.py
census_consumer_complaint_config/configuration.py
census_consumer_complaint_custom_component/__init__.py
census_consumer_complaint_custom_component/component.py
census_consumer_complaint_custom_component/example_gen/__init__.py
census_consumer_complaint_custom_component/example_gen/remote_zip_csv_example_gen/__init__.py
census_consumer_complaint_custom_component/example_gen/remote_zip_csv_example_gen/component.py
census_consumer_complaint_custom_component/example_gen/remote_zip_csv_example_gen/executor.py
census_consumer_complaint_custom_component/example_gen/remote_zip_csv_example_gen/executor_test.py
census_consumer_complaint_exception/__init__.py
census_consumer_complaint_exception/exception.py
census_consumer_complaint_orchestrator/__init__.py
census_consumer_complaint_orchestrator/airflow_orchestrator.py
census_consumer_complaint_orchestrator/apache_beam_orchestrator.py
census_consumer_complaint_orchestrator/interactive_context_runner.py
census_consumer_complaint_orchestrator/local_orchestrator.py
census_consumer_complaint_types/__init__.py
census_consumer_complaint_types/types.py
census_consumer_complaint_utils/__init__.py
census_consumer_complaint_ineuron-0.0.1.dist-info/METADATA
census_consumer_complaint_ineuron-0.0.1.dist-info/WHEEL
census_consumer_complaint_ineuron-0.0.1.dist-info/top_level.txt
census_consumer_complaint_ineuron-0.0.1.dist-info/RECORD
